[
  {
    "id": "1730886069675",
    "theme": "Music",
    "grid": [
      "SEGAHNES",
      "CCLGEDOD",
      "INCANGPR",
      "RAROCLMO",
      "YDTFBSEH",
      "LEYYXDTC",
      "SSRATIUG",
      "XTLPIANO"
    ],
    "wordsToFind": [
      "PIANO",
      "NOTES",
      "GUITAR",
      "TEMPO",
      "CHORD",
      "DANCE",
      "LYRICS",
      "SCALE"
    ]
  },
  {
    "id": "1730886120433",
    "theme": "Food",
    "grid": [
      "DPEACHBF",
      "KAETSZRD",
      "QPASTAES",
      "AXNALSAN",
      "FPPXUADA",
      "ESPSIUSE",
      "ELHLDCJB",
      "VIKOEEBP"
    ],
    "wordsToFind": [
      "BREAD",
      "APPLE",
      "PEACH",
      "PASTA",
      "SUSHI",
      "SAUCE",
      "BEANS",
      "STEAK"
    ]
  },
  {
    "id": "1730886152428",
    "theme": "Space",
    "grid": [
      "VJAGDXILJ",
      "STIBROCKD",
      "HQPYGOSXS",
      "TSFIMYRWA",
      "RXOEPRABL",
      "APTDDATLU",
      "EOMUWLSAB",
      "LUNAROTCE",
      "ONTBSSCKN"
    ],
    "wordsToFind": [
      "STARS",
      "NEBULA",
      "COMET",
      "ORBIT",
      "EARTH",
      "LUNAR",
      "SOLAR",
      "BLACK"
    ]
  },
  {
    "id": "1730886184349",
    "theme": "Nature",
    "grid": [
      "TREESQUD",
      "YCOHDFZU",
      "UECLSRTO",
      "ZNESEPNL",
      "DIAVAWAC",
      "FRIORWLL",
      "GRIRTQPO",
      "ZWECHVYK"
    ],
    "wordsToFind": [
      "RIVER",
      "FIELD",
      "PLANT",
      "EARTH",
      "TREES",
      "GRASS",
      "CLOUD"
    ]
  },
  {
    "id": "1730886231382",
    "theme": "Kitchen Utensils",
    "grid": [
      "GUMSPKZP",
      "OERVYRZL",
      "LWOBSOZA",
      "KSCPRFNT",
      "GNOJCPAE",
      "EOIHUOPE",
      "NXIFPTLR",
      "MWYGEFEU"
    ],
    "wordsToFind": [
      "KNIFE",
      "FORK",
      "SPOON",
      "BOWL",
      "PLATE",
      "CUP",
      "PAN",
      "POT"
    ]
  },
  {
    "id": "1730886265310",
    "theme": "School",
    "grid": [
      "UEBBNDG",
      "CMUEOQA",
      "CPPLZOB",
      "TYZWGIK",
      "LICNEPJ",
      "ERASERZ",
      "REPAPSJ"
    ],
    "wordsToFind": [
      "PEN",
      "PENCIL",
      "BOOK",
      "PAPER",
      "ERASER",
      "BAG",
      "GLUE"
    ]
  },
  {
    "id": "1730886409743",
    "theme": "Weather Conditions",
    "grid": [
      "QZYMROTSSG",
      "JRAELCSUAS",
      "SRIQKCNVIK",
      "ZNWSLNFHZY",
      "WOOOYFQTCT",
      "NRUWOWJRSE",
      "ODAGYHIWPR",
      "YDGIQCCNAD",
      "ZYFNNWUIDO",
      "BMHIRYUFTY"
    ],
    "wordsToFind": [
      "SUNNY",
      "RAINY",
      "CLOUDY",
      "WINDY",
      "FOGGY",
      "SNOWY",
      "STORMY",
      "CLEAR"
    ]
  },
  {
    "id": "1730884454893",
    "grid": [
      "FOXHCX",
      "EPDGCR",
      "ROOTFD",
      "GRARIR",
      "FCCZSI",
      "KGMBHB"
    ],
    "wordsToFind": [
      "CAT",
      "DOG",
      "FOX",
      "BIRD",
      "FISH",
      "FROG"
    ]
  },
  {
    "id": "1730884559346",
    "grid": [
      "GKCALBU",
      "WRTROXB",
      "HEEKETM",
      "IBIELDY",
      "TLPENXX",
      "EUPINKB",
      "YELLOWX"
    ],
    "wordsToFind": [
      "RED",
      "BLUE",
      "GREEN",
      "YELLOW",
      "BLACK",
      "WHITE",
      "PINK"
    ]
  },
  {
    "id": "1730884615568",
    "grid": [
      "SHCHIPRDM",
      "WFDVKLTRP",
      "ZOUNACAAN",
      "AHOPMABOE",
      "SCTBMBLBE",
      "VOKXOLEYR",
      "PZIZUETEC",
      "BOVHSLGKS",
      "PHONENMPW"
    ],
    "wordsToFind": [
      "PHONE",
      "LAPTOP",
      "TABLET",
      "MOUSE",
      "KEYBOARD",
      "SCREEN",
      "CABLE",
      "CHIP"
    ]
  },
  {
    "id": "1729318043916",
    "grid": [
      "NOILBA",
      "JUOTER",
      "EQOFAB",
      "TIGERE",
      "ESOOMZ",
      "ESROHT"
    ],
    "wordsToFind": [
      "TIGER",
      "BEAR",
      "LION",
      "ZEBRA",
      "HORSE",
      "MOOSE"
    ]
  },
  {
    "id": "1730884815147",
    "grid": [
      "TLFLAMEV",
      "CHHFEBSC",
      "SIGRYESL",
      "LTOINAAO",
      "XHONLCLU",
      "SNMNVHGD",
      "RPDJETZY",
      "XDXSSARG"
    ],
    "wordsToFind": [
      "FLAME",
      "GLASS",
      "STONE",
      "GRASS",
      "CLOUD",
      "BEACH",
      "SHORE",
      "LIGHT"
    ]
  },
  {
    "id": "1729314268025",
    "grid": [
      "LPMUSIBG",
      "HCTWUYTM",
      "KOWWPFCA",
      "RRAQOIIW",
      "AAVDTSMF",
      "HLEICHEK",
      "SGVGOEPX",
      "NGZMRSDE"
    ],
    "wordsToFind": [
      "WAVE",
      "SHARK",
      "CORAL",
      "FISH",
      "OCTOPUS",
      "REEF"
    ]
  },

  {
    "id": "1729314484294",
    "grid": [
      "MONKEY",
      "FLEAFD",
      "YFNOQY",
      "DRIBLL",
      "VOVZVS",
      "BGEERT"
    ],
    "wordsToFind": [
      "VINE",
      "TREE",
      "MONKEY",
      "BIRD",
      "FROG",
      "LEAF"
    ]
  },

  {
    "id": "1729314595091",
    "grid": [
      "XDDRUM",
      "RUAEKC",
      "WAIEWL",
      "LOEDAY",
      "MWLBHN",
      "RWOFNX"
    ],
    "wordsToFind": [
      "BEAR",
      "DEER",
      "LYNX",
      "WOLF",
      "OWL",
      "HAWK"
    ]
  },
  {
    "id": "1729314659651",
    "grid": [
      "JLPIHS",
      "NYRSSP",
      "TEVAWD",
      "FISHEG",
      "OGPMGP",
      "CORALI"
    ],
    "wordsToFind": [
      "FISH",
      "SHIP",
      "PEARL",
      "CORAL",
      "WAVE"
    ]
  },
  {
    "id": "1729314745084",
    "grid": [
      "KOALAM",
      "OLIONO",
      "FRLPZO",
      "REGITS",
      "WERHSE",
      "KZEBRA"
    ],
    "wordsToFind": [
      "LION",
      "ZEBRA",
      "KOALA",
      "TIGER",
      "SHREW",
      "MOOSE"
    ]
  },
  {
    "id": "1729314766926",
    "grid": [
      "NIARQA",
      "SCFOGS",
      "TNLHDU",
      "PJOOKN",
      "DNIWUP",
      "IILBVD"
    ],
    "wordsToFind": [
      "RAIN",
      "SNOW",
      "WIND",
      "CLOUD",
      "SUN",
      "FOG"
    ]
  },
  {
    "id": "1729317812354",
    "grid": [
      "GRAPEW",
      "JIHGDL",
      "DXKQDE",
      "QPEARM",
      "APPLEO",
      "MULPIN"
    ],
    "wordsToFind": [
      "APPLE",
      "PEAR",
      "GRAPE",
      "LEMON",
      "PLUM"
    ]
  },
  {
    "id": "1729317832848",
    "grid": [
      "NEFLEHSB",
      "CLPKRLRO",
      "BBSJAFHR",
      "RAGMDOIT",
      "ZTPHUABY",
      "WZBSHITV",
      "LEECISTH",
      "RVHHCUOC"
    ],
    "wordsToFind": [
      "HOUSE",
      "CHAIR",
      "TABLE",
      "LAMP",
      "SHELF",
      "COUCH"
    ]
  },
  {
    "id": "1729317881765",
    "grid": [
      "MTACOSPS",
      "VSEYXHUP",
      "DALASSIZ",
      "UQDXHZVL",
      "QGAIZEFP",
      "ZMEAZMGL",
      "XYRATSAP",
      "TRBKQFIL"
    ],
    "wordsToFind": [
      "PIZZA",
      "PASTA",
      "BREAD",
      "SALAD",
      "TACOS",
      "SUSHI"
    ]
  },
  {
    "id": "1729317909833",
    "grid": [
      "KNYXBOOK",
      "SZJPAPER",
      "RCFNJVNN",
      "IRESAREO",
      "WRELURPY",
      "WNYSMHAA",
      "PPENCILR",
      "HPLKRWHC"
    ],
    "wordsToFind": [
      "PENCIL",
      "PAPER",
      "ERASER",
      "RULER",
      "CRAYON",
      "BOOK"
    ]
  },
  {
    "id": "1729317994226",
    "grid": [
      "OCWONS",
      "DWSYMR",
      "FUIRRA",
      "KOONPI",
      "ATGLDN",
      "SBAVCB"
    ],
    "wordsToFind": [
      "CLOUD",
      "STORM",
      "WIND",
      "RAIN",
      "SNOW",
      "FOG"
    ]
  },
  {
    "id": "1729318013896",
    "grid": [
      "DOTBRZEH",
      "EOPUJLKS",
      "IMHWNYAS",
      "KQIEKOCG",
      "OFIWBODY",
      "OPXGVOQX",
      "CMYDNACR",
      "JELLYIXX"
    ],
    "wordsToFind": [
      "CANDY",
      "CAKE",
      "DONUT",
      "COOKIE",
      "PIE",
      "JELLY"
    ]
  }
]